w3lib/__init__.py
w3lib/_infra.py
w3lib/_types.py
w3lib/_url.py
w3lib/encoding.py
w3lib/html.py
w3lib/http.py
w3lib/py.typed
w3lib/url.py
w3lib/util.py
w3lib-2.3.0.dist-info/LICENSE
w3lib-2.3.0.dist-info/METADATA
w3lib-2.3.0.dist-info/WHEEL
w3lib-2.3.0.dist-info/top_level.txt
w3lib-2.3.0.dist-info/RECORD
